mathlib/__init__.py
mathlib/_seven.py
mathlib/_seven.pyi
mathlib/general.py
mathlib/numbers.py
mathlib/primes.py
mathlib/py.typed
mathlib-0.5.0.dist-info/LICENSE.txt
mathlib-0.5.0.dist-info/METADATA
mathlib-0.5.0.dist-info/WHEEL
mathlib-0.5.0.dist-info/RECORD
