Metadata-Version: 2.1
Name: mathlib
Version: 0.5.0
Summary: A pure-python maths library
Home-page: https://mathlib.readthedocs.io/en/stable/
License: LGPL-3.0+
Keywords: mathematics
Author: Stephanos Kuma
Author-email: stephanos@kuma.ai
Requires-Python: >=3.8,<4.0
Classifier: Development Status :: 4 - Beta
Classifier: Intended Audience :: Developers
Classifier: Intended Audience :: Science/Research
Classifier: License :: OSI Approved :: GNU Lesser General Public License v3 or later (LGPLv3+)
Classifier: Operating System :: OS Independent
Classifier: Programming Language :: Python :: 3
Classifier: Programming Language :: Python :: 3.8
Classifier: Programming Language :: Python :: 3.9
Classifier: Programming Language :: Python :: 3.10
Classifier: Programming Language :: Python :: 3.11
Classifier: Topic :: Scientific/Engineering :: Mathematics
Project-URL: Documentation, https://mathlib.readthedocs.io/en/stable/
Project-URL: Repository, https://github.com/spapanik/mathlib
